gate_sdk/__init__.py
gate_sdk/auth.py
gate_sdk/circuit_breaker.py
gate_sdk/client.py
gate_sdk/errors.py
gate_sdk/heartbeat.py
gate_sdk/http.py
gate_sdk/kms.py
gate_sdk/metrics.py
gate_sdk/provenance.py
gate_sdk/retry.py
gate_sdk/stepup.py
gate_sdk/types.py
gate_sdk/utils.py
gate_sdk/security/__init__.py
gate_sdk/security/iam_risk_checker.py
gate_sdk/signers/__init__.py
gate_sdk/signers/aws_kms.py
gate_sdk/signers/base.py
gate_sdk/signers/gcp_kms.py
gate_sdk/signers/vault.py
gate_sdk-0.3.7.dist-info/METADATA
gate_sdk-0.3.7.dist-info/WHEEL
gate_sdk-0.3.7.dist-info/RECORD
