Metadata-Version: 2.4
Name: gate-sdk
Version: 0.3.7
Summary: Production-grade Python SDK for BlockIntel Gate Hot Path API
Project-URL: Homepage, https://github.com/4KInc/blockintel-ai
Project-URL: Documentation, https://docs.blockintelai.com
Project-URL: Repository, https://github.com/4KInc/blockintel-ai
Project-URL: Issues, https://github.com/4KInc/blockintel-ai/issues
Author-email: BlockIntel <support@blockintelai.com>
License: MIT
Keywords: blockintel,crypto,defense,gate,sdk,security
Classifier: Development Status :: 4 - Beta
Classifier: Intended Audience :: Developers
Classifier: License :: OSI Approved :: MIT License
Classifier: Operating System :: OS Independent
Classifier: Programming Language :: Python :: 3
Classifier: Programming Language :: Python :: 3.9
Classifier: Programming Language :: Python :: 3.10
Classifier: Programming Language :: Python :: 3.11
Classifier: Programming Language :: Python :: 3.12
Requires-Python: >=3.9
Requires-Dist: httpx>=0.25.0
Provides-Extra: all
Requires-Dist: boto3>=1.28.0; extra == 'all'
Provides-Extra: dev
Requires-Dist: build>=1.0.0; extra == 'dev'
Requires-Dist: mypy>=1.5.0; extra == 'dev'
Requires-Dist: pytest-cov>=4.1.0; extra == 'dev'
Requires-Dist: pytest>=7.4.0; extra == 'dev'
Requires-Dist: respx>=0.20.0; extra == 'dev'
Requires-Dist: ruff>=0.1.0; extra == 'dev'
Requires-Dist: types-requests>=2.31.0; extra == 'dev'
Provides-Extra: kms
Requires-Dist: boto3>=1.28.0; extra == 'kms'
